ReconstructOrder/__init__.py
ReconstructOrder/cli_module.py
ReconstructOrder/compute/__init__.py
ReconstructOrder/compute/reconstruct.py
ReconstructOrder/tests/__init__.py
ReconstructOrder/tests/testMetrics.py
ReconstructOrder/utils/ConfigReader.py
ReconstructOrder/utils/__init__.py
ReconstructOrder/utils/imgIO.py
ReconstructOrder/utils/imgProcessing.py
ReconstructOrder/utils/mManagerIO.py
ReconstructOrder/utils/plotting.py
ReconstructOrder/workflow/__init__.py
ReconstructOrder/workflow/multiDimProcess.py
ReconstructOrder/workflow/reconstructBatch.py
sphinx-docs/__init__.py
ReconstructOrder-0.0.1.dist-info/LICENSE
ReconstructOrder-0.0.1.dist-info/METADATA
ReconstructOrder-0.0.1.dist-info/WHEEL
ReconstructOrder-0.0.1.dist-info/entry_points.txt
ReconstructOrder-0.0.1.dist-info/top_level.txt
ReconstructOrder-0.0.1.dist-info/RECORD
