Metadata-Version: 2.1
Name: ReconstructOrder
Version: 0.0.1
Summary: Reconstruct birefringence, slow axis, bright-field, and degree of polarization from polarization-resolved images.
Home-page: UNKNOWN
License: Chan Zuckerberg Biohub Software License
Download-URL: https://github.com/czbiohub/ReconstructOrder
Platform: UNKNOWN
Classifier: License :: OSI Approved :: BSD License
Classifier: Programming Language :: Python
Classifier: Programming Language :: Python :: 3 :: Only
Classifier: Programming Language :: Python :: 3.6
Classifier: Programming Language :: Python :: 3.7
Classifier: Topic :: Scientific/Engineering
Classifier: Topic :: Scientific/Engineering :: Visualization
Classifier: Topic :: Scientific/Engineering :: Information Analysis
Classifier: Topic :: Scientific/Engineering :: Bio-Informatics
Classifier: Topic :: Utilities
Classifier: Operating System :: Microsoft :: Windows
Classifier: Operating System :: POSIX
Classifier: Operating System :: Unix
Classifier: Operating System :: MacOS
Requires-Python: >=3.6
Requires-Dist: numpy (>=1.10.0)
Requires-Dist: opencv-python (>=3.4.2.16)
Requires-Dist: pandas (>=0.24.2)
Requires-Dist: pyyaml (>=3.13)
Requires-Dist: matplotlib (>=3.0.3)
Requires-Dist: scikit-image (>=0.15)
Requires-Dist: scipy (>=1.2.1)
